tensoneyroflow/__init__.py
tensoneyroflow/commands.py
tensoneyroflow/core.py
tensoneyroflow-0.1.0.dist-info/licenses/LICENSE
tensoneyroflow-0.1.0.dist-info/METADATA
tensoneyroflow-0.1.0.dist-info/WHEEL
tensoneyroflow-0.1.0.dist-info/top_level.txt
tensoneyroflow-0.1.0.dist-info/RECORD
