Metadata-Version: 2.4
Name: tensoneyroflow
Version: 0.1.0
Summary: A unified high-level API for TensorFlow, Keras and PyTorch
Author-email: mina903 <mina903@mail.ru>
License: 
Project-URL: Homepage, https://github.com/your-username/tensoneyroflow
Keywords: tensorflow,pytorch,keras,deep learning,wrapper
Classifier: License :: OSI Approved :: MIT License
Classifier: Programming Language :: Python
Classifier: Programming Language :: Python :: 3
Classifier: Programming Language :: Python :: 3.8
Classifier: Programming Language :: Python :: 3.9
Classifier: Programming Language :: Python :: 3.10
Classifier: Programming Language :: Python :: 3.11
License-File: LICENSE
Requires-Dist: tensorflow>=2.10.0
Requires-Dist: torch>=1.13.0
Requires-Dist: numpy>=1.21.0
Dynamic: license-file
